data2objects.py
data2objects-0.1.0.dist-info/LICENSE
data2objects-0.1.0.dist-info/METADATA
data2objects-0.1.0.dist-info/WHEEL
data2objects-0.1.0.dist-info/top_level.txt
data2objects-0.1.0.dist-info/RECORD
