Metadata-Version: 2.1
Name: data2objects
Version: 0.1.0
Summary: Transform nested data structures into Python objects
Author-email: John Gardner <gardner.john97@gmail.com>
License: MIT License
Project-URL: Homepage, https://github.com/jla-gardner/data2objects
Classifier: License :: OSI Approved :: MIT License
Classifier: Programming Language :: Python
Classifier: Programming Language :: Python :: 3
Requires-Python: >=3.8
License-File: LICENSE
Requires-Dist: pyyaml
Provides-Extra: dev
Requires-Dist: ruff; extra == "dev"
Requires-Dist: bumpver; extra == "dev"
Provides-Extra: publish
Requires-Dist: build; extra == "publish"
Requires-Dist: twine; extra == "publish"
